{
	"name": "pipeline3",
	"properties": {
		"activities": [
			{
				"name": "Lookup1",
				"type": "Lookup",
				"dependsOn": [],
				"policy": {
					"timeout": "0.12:00:00",
					"retry": 0,
					"retryIntervalInSeconds": 30,
					"secureOutput": false,
					"secureInput": false
				},
				"userProperties": [],
				"typeProperties": {
					"source": {
						"type": "DelimitedTextSource",
						"storeSettings": {
							"type": "AzureBlobFSReadSettings",
							"recursive": true,
							"enablePartitionDiscovery": false
						},
						"formatSettings": {
							"type": "DelimitedTextReadSettings"
						}
					},
					"dataset": {
						"referenceName": "ds_c1_order",
						"type": "DatasetReference",
						"parameters": {
							"Filepath": "Customer1/2023/05/csv/Prestage_csvfiles",
							"Filename": "c1order1.csv"
						}
					},
					"firstRowOnly": false
				}
			},
			{
				"name": "ForEach1",
				"type": "ForEach",
				"dependsOn": [
					{
						"activity": "Lookup1",
						"dependencyConditions": [
							"Succeeded"
						]
					}
				],
				"userProperties": [],
				"typeProperties": {
					"items": {
						"value": "@activity('Lookup1').output.value",
						"type": "Expression"
					},
					"activities": [
						{
							"name": "Get Metadata1",
							"type": "GetMetadata",
							"dependsOn": [
								{
									"activity": "Set variable1",
									"dependencyConditions": [
										"Succeeded"
									]
								}
							],
							"policy": {
								"timeout": "0.12:00:00",
								"retry": 0,
								"retryIntervalInSeconds": 30,
								"secureOutput": false,
								"secureInput": false
							},
							"userProperties": [],
							"typeProperties": {
								"dataset": {
									"referenceName": "ds_c1_order_graphicfile",
									"type": "DatasetReference",
									"parameters": {
										"graphicfilename": {
											"value": "@variables('filepath')",
											"type": "Expression"
										},
										"GraphicFilepath": {
											"value": "@concat('Customer1','/',substring(utcnow(),0,4),'/',substring(utcnow(),5,2),'/')",
											"type": "Expression"
										}
									}
								},
								"fieldList": [
									"exists"
								],
								"storeSettings": {
									"type": "AzureBlobFSReadSettings",
									"recursive": true,
									"enablePartitionDiscovery": false
								},
								"formatSettings": {
									"type": "DelimitedTextReadSettings"
								}
							}
						},
						{
							"name": "If Condition1",
							"type": "IfCondition",
							"dependsOn": [
								{
									"activity": "Get Metadata1",
									"dependencyConditions": [
										"Succeeded"
									]
								}
							],
							"userProperties": [],
							"typeProperties": {
								"expression": {
									"value": "@activity('Get Metadata1').output.exists",
									"type": "Expression"
								}
							}
						},
						{
							"name": "Set variable1",
							"type": "SetVariable",
							"dependsOn": [],
							"policy": {
								"secureOutput": false,
								"secureInput": false
							},
							"userProperties": [],
							"typeProperties": {
								"variableName": "filepath",
								"value": {
									"value": "@concat(item().Artikel,'_',item().Customername,'.pdf')",
									"type": "Expression"
								}
							}
						}
					]
				}
			}
		],
		"variables": {
			"filepath": {
				"type": "String"
			}
		},
		"folder": {
			"name": "Graphicfile"
		},
		"annotations": [],
		"lastPublishTime": "2023-06-01T11:46:23Z"
	},
	"type": "Microsoft.DataFactory/factories/pipelines"
}